tethys_gizmos
